frank/__init__.py
frank/frank.py
frank/module/__init__.py
frank/module/exceptions.py
frank/module/meta.py
frank/module/module.py
frank/module/decorators/__init__.py
frank/module/decorators/classes.py
frank/module/decorators/functions.py
frank/modules/__init__.py
frank/modules/help.py
frank_discord-0.1.0.dist-info/LICENSE
frank_discord-0.1.0.dist-info/METADATA
frank_discord-0.1.0.dist-info/WHEEL
frank_discord-0.1.0.dist-info/top_level.txt
frank_discord-0.1.0.dist-info/RECORD
